MANIFEST.in
README.md
setup.py
docs/release-notes.rst
pykwalify/__init__.py
pykwalify/cli.py
pykwalify/compat.py
pykwalify/core.py
pykwalify/errors.py
pykwalify/rule.py
pykwalify/types.py
pykwalify_unfixed.egg-info/PKG-INFO
pykwalify_unfixed.egg-info/SOURCES.txt
pykwalify_unfixed.egg-info/dependency_links.txt
pykwalify_unfixed.egg-info/entry_points.txt
pykwalify_unfixed.egg-info/requires.txt
pykwalify_unfixed.egg-info/top_level.txt
tests/__init__.py
tests/test_cli.py
tests/test_core.py
tests/test_core_methods.py
tests/test_exceptions.py
tests/test_helper.py
tests/test_rule.py
tests/test_types.py
tests/test_unicode.py
tests/files/README.md
tests/files/cli/1a.yaml
tests/files/cli/1b.yaml
tests/files/cli/2a.yaml
tests/files/cli/2b.yaml
tests/files/fail/10f.yaml
tests/files/fail/11f.yaml
tests/files/fail/12f.yaml
tests/files/fail/13f.yaml
tests/files/fail/14f.yaml
tests/files/fail/15f.yaml
tests/files/fail/16f.yaml
tests/files/fail/17f.yaml
tests/files/fail/18f.yaml
tests/files/fail/19f.yaml
tests/files/fail/1f.yaml
tests/files/fail/20f.yaml
tests/files/fail/21f.yaml
tests/files/fail/22f.yaml
tests/files/fail/23f.yaml
tests/files/fail/24f.yaml
tests/files/fail/2f.yaml
tests/files/fail/3f.yaml
tests/files/fail/4f.yaml
tests/files/fail/5f.yaml
tests/files/fail/6f.yaml
tests/files/fail/7f.yaml
tests/files/fail/8f.yaml
tests/files/fail/9f.yaml
tests/files/partial_schemas/1f-data.yaml
tests/files/partial_schemas/1f-partials.yaml
tests/files/partial_schemas/1f-schema.yaml
tests/files/partial_schemas/1s-data.yaml
tests/files/partial_schemas/1s-partials.yaml
tests/files/partial_schemas/1s-schema.yaml
tests/files/partial_schemas/2s-data.yaml
tests/files/partial_schemas/2s-partials.yaml
tests/files/partial_schemas/2s-schema.yaml
tests/files/success/10s.yaml
tests/files/success/11s.yaml
tests/files/success/12s.yaml
tests/files/success/13s.yaml
tests/files/success/14s.yaml
tests/files/success/15s.yaml
tests/files/success/16s.yaml
tests/files/success/17s.yaml
tests/files/success/18s.yaml
tests/files/success/19s.yaml
tests/files/success/1s.yaml
tests/files/success/20s.yaml
tests/files/success/21s.yaml
tests/files/success/22s.yaml
tests/files/success/23s.yaml
tests/files/success/24s.yaml
tests/files/success/25s.yaml
