Metadata-Version: 1.1
Name: pykwalify-unfixed
Version: 1.5.1
Summary: Python lib/cli for JSON/YAML schema validation
Home-page: http://github.com/grokzen/pykwalify
Author: Johan Andersson
Author-email: Grokzen@gmail.com
License: MIT
Platform: UNKNOWN
Classifier: Development Status :: 5 - Production/Stable
Classifier: Intended Audience :: Developers
Classifier: Operating System :: OS Independent
Classifier: License :: OSI Approved :: MIT License
Classifier: Environment :: Console
Classifier: Programming Language :: Python
Classifier: Programming Language :: Python :: 2.7
Classifier: Programming Language :: Python :: 3
Classifier: Programming Language :: Python :: 3.3
Classifier: Programming Language :: Python :: 3.4
